libindic/unicode_conversion_maps/__init__.py
libindic_unicode_conversion_maps-1.0.7958161057.dist-info/METADATA
libindic_unicode_conversion_maps-1.0.7958161057.dist-info/WHEEL
libindic_unicode_conversion_maps-1.0.7958161057.dist-info/top_level.txt
libindic_unicode_conversion_maps-1.0.7958161057.dist-info/RECORD
