Metadata-Version: 2.1
Name: libindic-unicode-conversion-maps
Version: 1.0.7958161057
Summary: Maps for converting ASCII to Unicode
Project-URL: Homepage, https://github.com/libindic/unicode-conversion-maps
